{
  "version": "2026.07.10-0700-rolling",
  "iso": {
    "name": "dozenos-2026.07.10-0700-rolling-generic-amd64.iso",
    "sha256": "310f207ebfa189bae994f92d5db1354d11faef2d4c5c36de2f6d99faf9af5d4d",
    "url": "https://github.com/dozenos/dozenos-nightly-build/releases/download/2026.07.10-0700-rolling/dozenos-2026.07.10-0700-rolling-generic-amd64.iso"
  },
  "minisig": {
    "name": "dozenos-2026.07.10-0700-rolling-generic-amd64.iso.minisig",
    "url": "https://github.com/dozenos/dozenos-nightly-build/releases/download/2026.07.10-0700-rolling/dozenos-2026.07.10-0700-rolling-generic-amd64.iso.minisig"
  },
  "artifacts": [
    {
      "flavor": "generic",
      "format": "iso",
      "name": "dozenos-2026.07.10-0700-rolling-generic-amd64.iso",
      "sha256": "310f207ebfa189bae994f92d5db1354d11faef2d4c5c36de2f6d99faf9af5d4d",
      "url": "https://github.com/dozenos/dozenos-nightly-build/releases/download/2026.07.10-0700-rolling/dozenos-2026.07.10-0700-rolling-generic-amd64.iso",
      "minisig": {
        "name": "dozenos-2026.07.10-0700-rolling-generic-amd64.iso.minisig",
        "url": "https://github.com/dozenos/dozenos-nightly-build/releases/download/2026.07.10-0700-rolling/dozenos-2026.07.10-0700-rolling-generic-amd64.iso.minisig"
      }
    },
    {
      "flavor": "kvm",
      "format": "iso",
      "name": "dozenos-2026.07.10-0700-rolling-kvm-amd64.iso",
      "sha256": "7d7af5fdd9efe458eb67c0cafc90c048919fd624d2e43a2287e355109ac081d6",
      "url": "https://github.com/dozenos/dozenos-nightly-build/releases/download/2026.07.10-0700-rolling/dozenos-2026.07.10-0700-rolling-kvm-amd64.iso",
      "minisig": {
        "name": "dozenos-2026.07.10-0700-rolling-kvm-amd64.iso.minisig",
        "url": "https://github.com/dozenos/dozenos-nightly-build/releases/download/2026.07.10-0700-rolling/dozenos-2026.07.10-0700-rolling-kvm-amd64.iso.minisig"
      }
    },
    {
      "flavor": "kvm",
      "format": "qcow2",
      "name": "dozenos-2026.07.10-0700-rolling-kvm-amd64.qcow2",
      "sha256": "209f4e0cfd747f570d21740b9e1921e9bae4fe215b860e74f07cb128c3e1bbdf",
      "url": "https://github.com/dozenos/dozenos-nightly-build/releases/download/2026.07.10-0700-rolling/dozenos-2026.07.10-0700-rolling-kvm-amd64.qcow2",
      "minisig": {
        "name": "dozenos-2026.07.10-0700-rolling-kvm-amd64.qcow2.minisig",
        "url": "https://github.com/dozenos/dozenos-nightly-build/releases/download/2026.07.10-0700-rolling/dozenos-2026.07.10-0700-rolling-kvm-amd64.qcow2.minisig"
      }
    }
  ],
  "minisign_pubkey_file": "minisign.pub",
  "published_at": "2026-07-10T09:09:36Z"
}
